setup.py
echrisantus_aws_ml/Binomialdistribution.py
echrisantus_aws_ml/Gaussiandistribution.py
echrisantus_aws_ml/Generaldistribution.py
echrisantus_aws_ml/__init__.py
echrisantus_aws_ml.egg-info/PKG-INFO
echrisantus_aws_ml.egg-info/SOURCES.txt
echrisantus_aws_ml.egg-info/dependency_links.txt
echrisantus_aws_ml.egg-info/not-zip-safe
echrisantus_aws_ml.egg-info/top_level.txt