Metadata-Version: 1.0
Name: echrisantus-aws-ml
Version: 0.1
Summary: Gaussian distributions
Home-page: UNKNOWN
Author: Chrisantus Eze
Author-email: ezechris30@gmail.com
License: UNKNOWN
Platform: UNKNOWN
